odoo/addons/web_advanced_filter/README.rst
odoo/addons/web_advanced_filter/__init__.py
odoo/addons/web_advanced_filter/__manifest__.py
odoo/addons/web_advanced_filter/i18n/advanced_filter.pot
odoo/addons/web_advanced_filter/i18n/de.po
odoo/addons/web_advanced_filter/i18n/fr.po
odoo/addons/web_advanced_filter/i18n/nl.po
odoo/addons/web_advanced_filter/i18n/tr.po
odoo/addons/web_advanced_filter/i18n/web_advanced_filter.pot
odoo/addons/web_advanced_filter/models/__init__.py
odoo/addons/web_advanced_filter/models/ir_filters.py
odoo/addons/web_advanced_filter/readme/CONTRIBUTORS.rst
odoo/addons/web_advanced_filter/readme/CREDITS.rst
odoo/addons/web_advanced_filter/readme/DESCRIPTION.rst
odoo/addons/web_advanced_filter/readme/ROADMAP.rst
odoo/addons/web_advanced_filter/readme/USAGE.rst
odoo/addons/web_advanced_filter/static/description/icon.png
odoo/addons/web_advanced_filter/static/description/index.html
odoo/addons/web_advanced_filter/static/src/css/web_advanced_filter.css
odoo/addons/web_advanced_filter/static/src/js/web_advanced_filter.js
odoo/addons/web_advanced_filter/static/src/xml/web_advanced_filter.xml
odoo/addons/web_advanced_filter/tests/__init__.py
odoo/addons/web_advanced_filter/tests/test_web_advanced_filter.py
odoo/addons/web_advanced_filter/views/ir_filters.xml
odoo/addons/web_advanced_filter/views/templates.xml
odoo/addons/web_advanced_filter/wizards/__init__.py
odoo/addons/web_advanced_filter/wizards/ir_filters_combine_with_existing.py
odoo/addons/web_advanced_filter/wizards/ir_filters_combine_with_existing.xml
odoo12_addon_web_advanced_filter-12.0.1.1.0.dist-info/METADATA
odoo12_addon_web_advanced_filter-12.0.1.1.0.dist-info/WHEEL
odoo12_addon_web_advanced_filter-12.0.1.1.0.dist-info/top_level.txt
odoo12_addon_web_advanced_filter-12.0.1.1.0.dist-info/RECORD
